README.rst
setup.py
postie/__init__.py
postie/mailer.py
postie/mixins.py
postie.egg-info/PKG-INFO
postie.egg-info/SOURCES.txt
postie.egg-info/dependency_links.txt
postie.egg-info/requires.txt
postie.egg-info/top_level.txt
test/test_mailer.py