Metadata-Version: 1.1
Name: postie
Version: 1.1.0
Summary: Simple Python library to manage SMTP configurations.
Home-page: https://github.com/tomleese/postie
Author: Tom Leese
Author-email: tom@tomleese.me.uk
License: UNKNOWN
Platform: UNKNOWN
Classifier: Topic :: Internet
Classifier: Development Status :: 5 - Production/Stable
Classifier: License :: OSI Approved :: MIT License
Classifier: Programming Language :: Python :: 2.7
Classifier: Programming Language :: Python :: 3
Classifier: Programming Language :: Python :: 3.2
Classifier: Programming Language :: Python :: 3.3
Classifier: Programming Language :: Python :: 3.4
